ezlogr/__init__.py
EZlogR-0.1.dist-info/METADATA
EZlogR-0.1.dist-info/WHEEL
EZlogR-0.1.dist-info/top_level.txt
EZlogR-0.1.dist-info/RECORD
