Metadata-Version: 2.1
Name: EZlogR
Version: 0.1
Summary: This is a simple logging tool to help devs focus on writing code instead of writing logs.
Home-page: http://www.ezlogr.com
Author: Jeremy Gillespie
Author-email: jeremy@kodeslingr.com
License: MIT
Platform: UNKNOWN
Requires-Python: >=3.6
